pandoclatexextensions/__init__.py
pandoclatexextensions/core.py
pandoc_latex_extensions-0.2.2.dist-info/AUTHORS
pandoc_latex_extensions-0.2.2.dist-info/LICENSE
pandoc_latex_extensions-0.2.2.dist-info/METADATA
pandoc_latex_extensions-0.2.2.dist-info/WHEEL
pandoc_latex_extensions-0.2.2.dist-info/entry_points.txt
pandoc_latex_extensions-0.2.2.dist-info/top_level.txt
pandoc_latex_extensions-0.2.2.dist-info/RECORD
