Metadata-Version: 2.1
Name: pandoc-latex-extensions
Version: 0.2.2
Summary: A pandoc filter that adds latex extensions.
Home-page: https://github.com/tomduck/pandoc-xnos
Author: Thomas J. Duck
Author-email: tomduck@tomduck.ca
License: GPL
Download-URL: https://github.com/tomduck/pandoc-latex-extensions/tarball/0.2.2
Keywords: pandoc latex extensions filter
Platform: UNKNOWN
Classifier: Development Status :: 3 - Alpha
Classifier: Intended Audience :: End Users/Desktop
Classifier: Environment :: Console
Classifier: License :: OSI Approved :: GNU General Public License v3 (GPLv3)
Classifier: Programming Language :: Python
Requires-Dist: pandocfilters (<2.0,>=1.4.2)
Requires-Dist: pandoc-xnos (<3.0,>=2.1.2)
